odoo/addons/product_search_category_attribute/README.rst
odoo/addons/product_search_category_attribute/__init__.py
odoo/addons/product_search_category_attribute/__manifest__.py
odoo/addons/product_search_category_attribute/i18n/es.po
odoo/addons/product_search_category_attribute/models/__init__.py
odoo/addons/product_search_category_attribute/models/product_search_category_attribute.py
odoo/addons/product_search_category_attribute/models/product_search_category_attribute_line.py
odoo/addons/product_search_category_attribute/readme/CONTRIBUTORS.md
odoo/addons/product_search_category_attribute/readme/DESCRIPTION.md
odoo/addons/product_search_category_attribute/readme/USAGE.md
odoo/addons/product_search_category_attribute/security/ir.model.access.csv
odoo/addons/product_search_category_attribute/static/description/icon.png
odoo/addons/product_search_category_attribute/static/description/index.html
odoo/addons/product_search_category_attribute/views/product_search_category_attribute_views.xml
odoo/addons/product_search_category_attribute/wizards/__init__.py
odoo/addons/product_search_category_attribute/wizards/product_search_cat_attr_category.py
odoo_addon_product_search_category_attribute-16.0.1.0.0.2.dist-info/METADATA
odoo_addon_product_search_category_attribute-16.0.1.0.0.2.dist-info/WHEEL
odoo_addon_product_search_category_attribute-16.0.1.0.0.2.dist-info/top_level.txt
odoo_addon_product_search_category_attribute-16.0.1.0.0.2.dist-info/RECORD
